<?xml version="1.0" encoding="UTF-8"?>
<Tokens version="1.0">
	<File path="Categories/NSDictionary+Attributes.html">
		
		<Token>
			<TokenIdentifier>//apple_ref/occ/cat/NSDictionary(Attributes)</TokenIdentifier>
			<Abstract type="html"></Abstract>
			<DeclaredIn>NSDictionary+Attributes.h</DeclaredIn>
            
			
			<NodeRef refid="4"/>
		</Token>
		
		
		<Token>
			<TokenIdentifier>//apple_ref/occ/instm/NSDictionary/attributesWithFontType:pointSize:andColor:</TokenIdentifier>
			<Abstract type="html"></Abstract>
			<DeclaredIn>NSDictionary+Attributes.h</DeclaredIn>
			
			<Declaration>+ (instancetype)attributesWithFontType:(FontType)fontType pointSize:(CGFloat)pointSize andColor:(UIColor *)color</Declaration>
			
			
			<Anchor>//api/name/attributesWithFontType:pointSize:andColor:</Anchor>
            <NodeRef refid="4"/>
		</Token>
		
		<Token>
			<TokenIdentifier>//apple_ref/occ/instm/NSDictionary/attributesWithFont:textColor:</TokenIdentifier>
			<Abstract type="html"></Abstract>
			<DeclaredIn>NSDictionary+Attributes.h</DeclaredIn>
			
			<Declaration>+ (instancetype)attributesWithFont:(UIFont *)font textColor:(UIColor *)textColor</Declaration>
			
			
			<Anchor>//api/name/attributesWithFont:textColor:</Anchor>
            <NodeRef refid="4"/>
		</Token>
		
		<Token>
			<TokenIdentifier>//apple_ref/occ/instm/NSDictionary/attributesWithFont:textColor:lineSpacing:</TokenIdentifier>
			<Abstract type="html"></Abstract>
			<DeclaredIn>NSDictionary+Attributes.h</DeclaredIn>
			
			<Declaration>+ (instancetype)attributesWithFont:(UIFont *)font textColor:(UIColor *)textColor lineSpacing:(CGFloat)lineSpacing</Declaration>
			
			
			<Anchor>//api/name/attributesWithFont:textColor:lineSpacing:</Anchor>
            <NodeRef refid="4"/>
		</Token>
		
        
        
	</File>
</Tokens>